Metadata-Version: 2.1
Name: newBiswapack
Version: 0.0.1
Summary: BMI TRIAL PACKAGE.
Home-page: UNKNOWN
Author: BISWATOSH PURKAYASTHA
Author-email: bppsah@gmail.com
License: MIT
Platform: UNKNOWN
License-File: licence.txt
